unique_code_snippets/__init__.py
unique_code_snippets/code_snippets.py
unique_code_snippets-0.1.0.dist-info/LICENSE
unique_code_snippets-0.1.0.dist-info/METADATA
unique_code_snippets-0.1.0.dist-info/WHEEL
unique_code_snippets-0.1.0.dist-info/top_level.txt
unique_code_snippets-0.1.0.dist-info/RECORD
