Metadata-Version: 2.1
Name: unique_code_snippets
Version: 0.1.0
Summary: A package that provides unique code snippets for various functionalities.
Home-page: https://github.com/yourusername/unique_code_snippets
Author: ll
Author-email: your.email@example.com
License: UNKNOWN
Platform: UNKNOWN
Classifier: Programming Language :: Python :: 3
Classifier: License :: OSI Approved :: MIT License
Classifier: Operating System :: OS Independent
License-File: LICENSE
